nolan.so
nolan-0.1.5.dist-info/DESCRIPTION.rst
nolan-0.1.5.dist-info/METADATA
nolan-0.1.5.dist-info/RECORD
nolan-0.1.5.dist-info/WHEEL
nolan-0.1.5.dist-info/eager_resources.txt
nolan-0.1.5.dist-info/metadata.json
nolan-0.1.5.dist-info/top_level.txt
