Metadata-Version: 2.0
Name: nolan
Version: 0.1.5
Summary: This is module can be used to make paralle http requests.
Home-page: UNKNOWN
Author: UNKNOWN
Author-email: UNKNOWN
License: UNKNOWN
Platform: UNKNOWN
